MANIFEST.in
README.md
setup.py
xhs_spider/__init__.py
xhs_spider/home.py
xhs_spider/one.py
xhs_spider/profile.py
xhs_spider/search.py
xhs_spider.egg-info/PKG-INFO
xhs_spider.egg-info/SOURCES.txt
xhs_spider.egg-info/dependency_links.txt
xhs_spider.egg-info/requires.txt
xhs_spider.egg-info/top_level.txt
xhs_spider/pojo/__init__.py
xhs_spider/pojo/note.py
xhs_spider/pojo/user.py
xhs_spider/static/__init__.py
xhs_spider/static/cookies.txt
xhs_spider/static/info.js
xhs_spider/xhs_utils/__init__.py
xhs_spider/xhs_utils/cookie_util.py
xhs_spider/xhs_utils/xhs_util.py