Metadata-Version: 2.1
Name: xhs-spider
Version: 1.1.0
Summary: Little Red Book notes, home page, detailed page crawler
Author: cv_cat
Author-email: 
Keywords: python,xhs,spider
Classifier: Development Status :: 1 - Planning
Classifier: Intended Audience :: Developers
Classifier: Programming Language :: Python :: 3.6
Classifier: Operating System :: Unix
Classifier: Operating System :: MacOS :: MacOS X
Classifier: Operating System :: Microsoft :: Windows
